frc_apriltags/__init__.py
frc_apriltags/apriltags.py
frc_apriltags/calibration.py
frc_apriltags/camera.py
frc_apriltags/communications.py
frc_apriltags/stream.py
frc_apriltags/Tag_Layouts/2023-chargedup.json
frc_apriltags/Tag_Layouts/__init__.py
frc_apriltags/Utilities/AprilTag.py
frc_apriltags/Utilities/AprilTagFieldLayout.py
frc_apriltags/Utilities/Logger.py
frc_apriltags/Utilities/MathUtil.py
frc_apriltags/Utilities/Units.py
frc_apriltags/Utilities/__init__.py
frc_apriltags-1.3.2.dist-info/LICENSE.txt
frc_apriltags-1.3.2.dist-info/METADATA
frc_apriltags-1.3.2.dist-info/WHEEL
frc_apriltags-1.3.2.dist-info/top_level.txt
frc_apriltags-1.3.2.dist-info/RECORD
