Metadata-Version: 2.1
Name: frc-apriltags
Version: 1.3.2
Summary: AprilTag detection for FRC robots
Author-email: Alex Pereira <robolionsgit@gmail.com>
Maintainer-email: The Robo-Lions <robolionsgit@gmail.com>
License: MIT License
Project-URL: Homepage, https://github.com/PIE-Cubed/FRC-AprilTags
Project-URL: Documentation, https://frc-apriltags.readthedocs.io/en/stable/
Project-URL: Bug Reports, https://github.com/PIE-Cubed/FRC-AprilTags/issues
Project-URL: Funding, https://www.pie3.org/support-pie3.html
Project-URL: Source, https://github.com/PIE-Cubed/FRC-AprilTags
Keywords: FRC-AprilTags,FRC,AprilTags,OpenCV
Classifier: Development Status :: 5 - Production/Stable
Classifier: Intended Audience :: Developers
Classifier: Intended Audience :: Education
Classifier: Topic :: Scientific/Engineering
Classifier: Topic :: Software Development
Classifier: Topic :: Software Development :: Testing
Classifier: License :: OSI Approved :: MIT License
Classifier: Programming Language :: Python :: 3
Classifier: Programming Language :: Python :: 3.8
Classifier: Programming Language :: Python :: 3.9
Classifier: Programming Language :: Python :: 3.10
Classifier: Programming Language :: Python :: 3.11
Classifier: Programming Language :: Python :: 3 :: Only
Requires-Python: <3.12,>=3.8
License-File: LICENSE.txt
Requires-Dist: pupil-apriltags (>=1.0.4)
Requires-Dist: robotpy[cscore] (>=2023.4.3)
Requires-Dist: pynetworktables (>=2021.0.0)
Requires-Dist: opencv-contrib-python (>=4.7.0)
Requires-Dist: importlib-metadata (>=6.0.0)
